pypi_server/__init__.py
pypi_server/cache.py
pypi_server/hash_version.py
pypi_server/http_cache.py
pypi_server/server.py
pypi_server/timeit.py
pypi_server/db/__init__.py
pypi_server/db/groups.py
pypi_server/db/packages.py
pypi_server/db/rules.py
pypi_server/db/users.py
pypi_server/db/migrator/__init__.py
pypi_server/db/migrator/actions.py
pypi_server/db/migrator/model.py
pypi_server/db/migrator/migrations/001_create_tables.py
pypi_server/db/migrator/migrations/002_create_default_user.py
pypi_server/db/migrator/migrations/003_create_package_tables.py
pypi_server/db/migrator/migrations/004_packagefile_add_url_and_fetched.py
pypi_server/db/migrator/migrations/005_packagefile_basename_unique.py
pypi_server/db/migrator/migrations/006_packageversion_license_textfield.py
pypi_server/db/migrator/migrations/__init__.py
pypi_server/handlers/__init__.py
pypi_server/handlers/base.py
pypi_server/handlers/default.py
pypi_server/handlers/index.py
pypi_server/handlers/api/__init__.py
pypi_server/handlers/api/login.py
pypi_server/handlers/api/package.py
pypi_server/handlers/api/packages.py
pypi_server/handlers/api/user.py
pypi_server/handlers/api/users.py
pypi_server/handlers/api/version.py
pypi_server/handlers/pypi/__init__.py
pypi_server/handlers/pypi/package.py
pypi_server/handlers/pypi/proxy/__init__.py
pypi_server/handlers/pypi/proxy/client.py
pypi_server/handlers/pypi/simple/__init__.py
pypi_server/handlers/pypi/simple/files.py
pypi_server/handlers/pypi/simple/packages.py
pypi_server/static/.DS_Store
pypi_server/static/css/simple.css
pypi_server/static/css/style.css
pypi_server/static/css/ui-bootstrap-custom-0.14.3-csp.css
pypi_server/static/favicon/apple-touch-icon-114x114.png
pypi_server/static/favicon/apple-touch-icon-120x120.png
pypi_server/static/favicon/apple-touch-icon-144x144.png
pypi_server/static/favicon/apple-touch-icon-152x152.png
pypi_server/static/favicon/apple-touch-icon-57x57.png
pypi_server-0.4.7.dist-info/DESCRIPTION.rst
pypi_server-0.4.7.dist-info/METADATA
pypi_server-0.4.7.dist-info/RECORD
pypi_server-0.4.7.dist-info/WHEEL
pypi_server-0.4.7.dist-info/entry_points.txt
pypi_server-0.4.7.dist-info/metadata.json
pypi_server-0.4.7.dist-info/top_level.txt
